vatvalidate/__init__.py
vatvalidate/exceptions.py
vatvalidate/py.typed
vatvalidate/validate.py
vatvalidate-0.1.0.dist-info/METADATA
vatvalidate-0.1.0.dist-info/WHEEL
vatvalidate-0.1.0.dist-info/licenses/LICENSE
vatvalidate-0.1.0.dist-info/RECORD
