Metadata-Version: 2.4
Name: vatvalidate
Version: 0.1.0
Summary: vatvalidate is a Python library for validating UK VAT numbers.
Author-email: Beauhurst Devs <dev@beauhurst.com>
License-Expression: MIT
License-File: LICENSE
Classifier: Operating System :: OS Independent
Classifier: Programming Language :: Python :: 3
Classifier: Programming Language :: Python :: 3 :: Only
Classifier: Programming Language :: Python :: 3.11
Classifier: Programming Language :: Python :: 3.12
Classifier: Programming Language :: Python :: 3.13
Requires-Python: <3.15,>=3.11
